kclip.py
kclip-1.0.1.dist-info/LICENSE.txt
kclip-1.0.1.dist-info/METADATA
kclip-1.0.1.dist-info/WHEEL
kclip-1.0.1.dist-info/top_level.txt
kclip-1.0.1.dist-info/RECORD
