Metadata-Version: 2.1
Name: kclip
Version: 1.0.1
Summary: Parse Kindle Clippings text file
Home-page: https://github.com/jbsmithjj/kclip
Author: Jeremy B. Smith
Author-email: jbsmithjj@gmail.com
License: MIT
Platform: UNKNOWN
